pas.plugins.memberpropertytogroup-3.0.0-py3.10-nspkg.pth
pas/plugins/memberpropertytogroup/__init__.py
pas/plugins/memberpropertytogroup/configure.zcml
pas/plugins/memberpropertytogroup/interfaces.py
pas/plugins/memberpropertytogroup/plugin.py
pas/plugins/memberpropertytogroup/setuphandlers.py
pas/plugins/memberpropertytogroup/testing.py
pas/plugins/memberpropertytogroup/upgrades.py
pas/plugins/memberpropertytogroup/upgrades.zcml
pas/plugins/memberpropertytogroup/browser/__init__.py
pas/plugins/memberpropertytogroup/browser/add_plugin.pt
pas/plugins/memberpropertytogroup/browser/configure.zcml
pas/plugins/memberpropertytogroup/browser/controlpanel.py
pas/plugins/memberpropertytogroup/browser/mptg.png
pas/plugins/memberpropertytogroup/browser/mptg_form.pt
pas/plugins/memberpropertytogroup/browser/mptg_helper.css
pas/plugins/memberpropertytogroup/browser/mptg_helper.js
pas/plugins/memberpropertytogroup/locales/pas.plugins.memberpropertytogroup.pot
pas/plugins/memberpropertytogroup/locales/update.py
pas/plugins/memberpropertytogroup/locales/en/LC_MESSAGES/pas.plugins.memberpropertytogroup.po
pas/plugins/memberpropertytogroup/profiles/default/browserlayer.xml
pas/plugins/memberpropertytogroup/profiles/default/controlpanel.xml
pas/plugins/memberpropertytogroup/profiles/default/import_steps.xml
pas/plugins/memberpropertytogroup/profiles/default/metadata.xml
pas/plugins/memberpropertytogroup/profiles/default/paspluginsmemberpropertytogroup_marker.txt
pas/plugins/memberpropertytogroup/profiles/default/registry.xml
pas/plugins/memberpropertytogroup/profiles/uninstall/browserlayer.xml
pas/plugins/memberpropertytogroup/profiles/uninstall/controlpanel.xml
pas/plugins/memberpropertytogroup/profiles/uninstall/registry.xml
pas/plugins/memberpropertytogroup/tests/__init__.py
pas/plugins/memberpropertytogroup/tests/test_robot.py
pas/plugins/memberpropertytogroup/tests/robot/test_acceptance.robot
pas.plugins.memberpropertytogroup-3.0.0.dist-info/METADATA
pas.plugins.memberpropertytogroup-3.0.0.dist-info/WHEEL
pas.plugins.memberpropertytogroup-3.0.0.dist-info/entry_points.txt
pas.plugins.memberpropertytogroup-3.0.0.dist-info/namespace_packages.txt
pas.plugins.memberpropertytogroup-3.0.0.dist-info/top_level.txt
pas.plugins.memberpropertytogroup-3.0.0.dist-info/RECORD
