Metadata-Version: 2.1
Name: pas.plugins.memberpropertytogroup
Version: 3.0.0
Summary: Plone PAS plugin to create virtual groups based on member properties
Home-page: http://pypi.python.org/pypi/pas.plugins.memberpropertytogroup
Author: kitconcept GmbH
Author-email: info@kitconcept.com
License: GPL
Keywords: Python Plone PAS LDAP
Classifier: Development Status :: 5 - Production/Stable
Classifier: Environment :: Web Environment
Classifier: Framework :: Plone
Classifier: Framework :: Plone :: Addon
Classifier: Framework :: Plone :: 6.0
Classifier: Programming Language :: Python
Classifier: Programming Language :: Python :: 3.8
Classifier: Programming Language :: Python :: 3.9
Classifier: Programming Language :: Python :: 3.10
Classifier: Programming Language :: Python :: 3.11
Classifier: Operating System :: OS Independent
Classifier: License :: OSI Approved :: GNU General Public License v2 (GPLv2)
Requires-Python: >=3.8
Requires-Dist: Plone
Requires-Dist: setuptools
Provides-Extra: test
Requires-Dist: gocept.pytestlayer ; extra == 'test'
Requires-Dist: mock ; extra == 'test'
Requires-Dist: plone.app.testing ; extra == 'test'
Requires-Dist: plone.app.robotframework[debug] ; extra == 'test'
Requires-Dist: plone.restapi[test] ; extra == 'test'
Requires-Dist: pytest ; extra == 'test'
Requires-Dist: pytest-mock ; extra == 'test'
Requires-Dist: pytest-cov ; extra == 'test'
